{
  "ticker": "058470",
  "name": "리노공업",
  "market": "KOSDAQ",
  "events": [
    {
      "date": "20260609",
      "change_rate": 16.33,
      "close_price": 99000.0,
      "trading_volume": 1591656,
      "trading_value": 157573944000,
      "rise_reason": "기관 순매수 보도",
      "reason_confidence": "high",
      "reason_source": "stockrise",
      "reason_status": "filled",
      "theme_tag": "반도체 장비",
      "news": [
        {
          "title": "하루만에 반등…코스피 8%대 상승 마감",
          "link": "https://finance.naver.com/item/news_read.naver?article_id=0001254804&office_id=215&code=058470&page=&sm=",
          "source": "한국경제TV",
          "date": "2026.06.09"
        },
        {
          "title": "코스피, '검은 월요일' 딛고 8000선 재탈환…역대 최대 상승폭",
          "link": "https://finance.naver.com/item/news_read.naver?article_id=0013996460&office_id=003&code=058470&page=&sm=",
          "source": "뉴시스",
          "date": "2026.06.09"
        },
        {
          "title": "코스피, 하루 만에 8%대 급반등…8000선 회복",
          "link": "https://finance.naver.com/item/news_read.naver?article_id=0002384400&office_id=123&code=058470&page=&sm=",
          "source": "조세일보",
          "date": "2026.06.09"
        },
        {
          "title": "코스피, 급락 딛고 8000선 탈환…기관 '사자'에 강세",
          "link": "https://finance.naver.com/item/news_read.naver?article_id=0000506229&office_id=629&code=058470&page=&sm=",
          "source": "더팩트",
          "date": "2026.06.09"
        },
        {
          "title": "'롤러코스피' 기관 조단위 순매수에 단숨에 8100선 추격",
          "link": "https://finance.naver.com/item/news_read.naver?article_id=0005369348&office_id=008&code=058470&page=&sm=",
          "source": "머니투데이",
          "date": "2026.06.09"
        },
        {
          "title": "\"어제오늘 코스피에 무슨 일이\"...8% 급락했다 8% 급등했다 [fn...",
          "link": "https://finance.naver.com/item/news_read.naver?article_id=0005532620&office_id=014&code=058470&page=&sm=",
          "source": "파이낸셜뉴스",
          "date": "2026.06.09"
        },
        {
          "title": "'붉은 화요일'…8% 급등 코스피, 8090선 회복 [시황]",
          "link": "https://finance.naver.com/item/news_read.naver?article_id=0003099287&office_id=119&code=058470&page=&sm=",
          "source": "데일리안",
          "date": "2026.06.09"
        },
        {
          "title": "반도체·로봇·2차전지…'성장주 베팅' 코스닥 ETF 쏟아진다",
          "link": "https://finance.naver.com/item/news_read.naver?article_id=0005296704&office_id=015&code=058470&page=&sm=",
          "source": "한국경제",
          "date": "2026.06.09"
        },
        {
          "title": "‘급락 하루만에 급등’ 코스피, 8000선 회복…기관 2.5조원 순매수",
          "link": "https://finance.naver.com/item/news_read.naver?article_id=0005691364&office_id=009&code=058470&page=&sm=",
          "source": "매일경제",
          "date": "2026.06.09"
        }
      ],
      "sector": "반도체와반도체장비",
      "is_52w_high": false,
      "source": "stockrise"
    },
    {
      "date": "20260403",
      "change_rate": 11.4,
      "close_price": 110400.0,
      "trading_volume": 934117,
      "trading_value": 103126516800,
      "rise_reason": "52주 신고가 도달",
      "reason_confidence": "mid",
      "reason_source": "pattern",
      "reason_status": "filled",
      "theme_tag": "반도체 장비",
      "news": [],
      "sector": "반도체와반도체장비",
      "is_52w_high": true,
      "source": "estimated"
    },
    {
      "date": "20260401",
      "change_rate": 10.81,
      "close_price": 104600.0,
      "trading_volume": 725098,
      "trading_value": 75845250800,
      "rise_reason": "52주 신고가 도달",
      "reason_confidence": "mid",
      "reason_source": "pattern",
      "reason_status": "filled",
      "theme_tag": "반도체 장비",
      "news": [],
      "sector": "반도체와반도체장비",
      "is_52w_high": true,
      "source": "estimated"
    },
    {
      "date": "20260305",
      "change_rate": 20.32,
      "close_price": 121400.0,
      "rise_reason": "반도체 장비 테마 강세",
      "reason_confidence": "low",
      "reason_source": "theme",
      "reason_status": "filled",
      "theme_tag": "반도체 장비",
      "news": [],
      "sector": "반도체와반도체장비",
      "is_52w_high": false,
      "source": "estimated",
      "trading_volume": 2584339,
      "trading_value": 313738754600,
      "market_cap": 9252095896328
    },
    {
      "date": "20260130",
      "change_rate": 14.98,
      "close_price": 105900.0,
      "rise_reason": "52주 신고가 도달",
      "reason_confidence": "mid",
      "reason_source": "pattern",
      "reason_status": "filled",
      "theme_tag": "반도체 장비",
      "news": [],
      "sector": "반도체와반도체장비",
      "is_52w_high": true,
      "source": "estimated",
      "trading_volume": 3108007,
      "trading_value": 329137941300,
      "market_cap": 8070815118790
    },
    {
      "date": "20260127",
      "change_rate": 10.62,
      "close_price": 83300.0,
      "rise_reason": "52주 신고가 도달",
      "reason_confidence": "mid",
      "reason_source": "pattern",
      "reason_status": "filled",
      "theme_tag": "반도체 장비",
      "news": [],
      "sector": "반도체와반도체장비",
      "is_52w_high": true,
      "source": "estimated",
      "trading_volume": 2020852,
      "trading_value": 168336971600,
      "market_cap": 6348431533477
    },
    {
      "date": "20251125",
      "change_rate": 11.88,
      "close_price": 63100.0,
      "rise_reason": "52주 신고가 도달",
      "reason_confidence": "mid",
      "reason_source": "pattern",
      "reason_status": "filled",
      "theme_tag": "반도체 장비",
      "news": [],
      "sector": "반도체와반도체장비",
      "is_52w_high": true,
      "source": "estimated",
      "trading_volume": 2804197,
      "trading_value": 176944830700,
      "market_cap": 4808955939524
    }
  ],
  "stats": {
    "count_10": 7,
    "count_15": 2,
    "count_20": 1,
    "count_limit": 0,
    "count_recent": 0,
    "avg_rate": 13.76
  },
  "built_at": "2026-07-10T16:19:49"
}