{
  "ticker": "064400",
  "name": "LG씨엔에스",
  "market": "KOSPI",
  "events": [
    {
      "date": "20260514",
      "change_rate": 17.14,
      "close_price": 86100.0,
      "rise_reason": "실적 성장",
      "reason_confidence": "high",
      "reason_source": "stockrise",
      "reason_status": "filled",
      "theme_tag": "SI(시스템통합)",
      "news": [
        {
          "title": "[어제장 오늘장] 쉽게 무너지지 않는 반도체주…조정 시엔 저가매수세.....",
          "link": "https://finance.naver.com/item/news_read.naver?article_id=0000510031&office_id=374&code=064400&page=&sm=",
          "source": "SBS Biz",
          "date": "2026.05.14"
        },
        {
          "title": "\"파인튜닝은 과대평가…AI 성능, 데이터 품질이 결정\"",
          "link": "https://finance.naver.com/item/news_read.naver?article_id=0002227904&office_id=138&code=064400&page=&sm=",
          "source": "디지털데일리",
          "date": "2026.05.14"
        },
        {
          "title": "SK AX도 오픈AI 동맹 합류…IT서비스 업계, 실행형 AI 경쟁 가...",
          "link": "https://finance.naver.com/item/news_read.naver?article_id=0002422732&office_id=092&code=064400&page=&sm=",
          "source": "지디넷코리아",
          "date": "2026.05.14"
        },
        {
          "title": "SK AX, 오픈AI 손잡고 기업용 AI 사업 확대",
          "link": "https://finance.naver.com/item/news_read.naver?article_id=0004620674&office_id=011&code=064400&page=&sm=",
          "source": "서울경제",
          "date": "2026.05.14"
        },
        {
          "title": "오픈AI 손잡는 IT서비스업계…SK AX, '챗GPT 엔터프라이즈' ...",
          "link": "https://finance.naver.com/item/news_read.naver?article_id=0002227807&office_id=138&code=064400&page=&sm=",
          "source": "디지털데일리",
          "date": "2026.05.14"
        },
        {
          "title": "LG, 인재 확보 전선 알파세대·글로벌로 넓혔다…'One LG' 승부수",
          "link": "https://finance.naver.com/item/news_read.naver?article_id=0003427642&office_id=030&code=064400&page=&sm=",
          "source": "전자신문",
          "date": "2026.05.14"
        },
        {
          "title": "'LG 테크 콘퍼런스'에 계열사 최고경영진 총출동…알파세대·석박사 미...",
          "link": "https://finance.naver.com/item/news_read.naver?article_id=0000499102&office_id=629&code=064400&page=&sm=",
          "source": "더팩트",
          "date": "2026.05.14"
        },
        {
          "title": "LG, 알파세대부터 국내외 석·박사까지 인재확보 '테크 콘퍼런스'",
          "link": "https://finance.naver.com/item/news_read.naver?article_id=0005357549&office_id=008&code=064400&page=&sm=",
          "source": "머니투데이",
          "date": "2026.05.14"
        },
        {
          "title": "LG, 알파세대 영재까지 품었다…AI 시대 '미래 인재 선점' 총력",
          "link": "https://finance.naver.com/item/news_read.naver?article_id=0003090283&office_id=119&code=064400&page=&sm=",
          "source": "데일리안",
          "date": "2026.05.14"
        },
        {
          "title": "LG, ‘미래 기술 인재’ 확보 나선다",
          "link": "https://finance.naver.com/item/news_read.naver?article_id=0001380674&office_id=082&code=064400&page=&sm=",
          "source": "부산일보",
          "date": "2026.05.14"
        }
      ],
      "sector": "IT서비스",
      "is_52w_high": false,
      "source": "stockrise"
    },
    {
      "date": "20260115",
      "change_rate": 10.19,
      "close_price": 68100.0,
      "rise_reason": "",
      "reason_confidence": "low",
      "reason_source": "naver",
      "reason_status": "missing",
      "theme_tag": "",
      "news": [],
      "sector": "",
      "is_52w_high": false,
      "source": "estimated"
    },
    {
      "date": "20250616",
      "change_rate": 11.27,
      "close_price": 71100.0,
      "rise_reason": "52주 신고가 도달",
      "reason_confidence": "mid",
      "reason_source": "pattern",
      "reason_status": "filled",
      "theme_tag": "",
      "news": [],
      "sector": "",
      "is_52w_high": true,
      "source": "estimated"
    },
    {
      "date": "20250612",
      "change_rate": 11.95,
      "close_price": 59000.0,
      "rise_reason": "52주 신고가 도달",
      "reason_confidence": "mid",
      "reason_source": "pattern",
      "reason_status": "filled",
      "theme_tag": "",
      "news": [],
      "sector": "",
      "is_52w_high": true,
      "source": "estimated"
    }
  ],
  "stats": {
    "count_10": 4,
    "count_15": 1,
    "count_20": 0,
    "count_limit": 0,
    "count_recent": 1,
    "avg_rate": 12.64
  },
  "built_at": "2026-05-17T06:57:01"
}