{
  "ticker": "100590",
  "name": "머큐리",
  "market": "KOSDAQ",
  "events": [
    {
      "date": "20260511",
      "change_rate": 16.17,
      "close_price": 10850.0,
      "rise_reason": "증권사 리포트 공개",
      "reason_confidence": "high",
      "reason_source": "stockrise",
      "reason_status": "filled",
      "theme_tag": "광통신(광케이블/광섬유 등)",
      "news": [
        {
          "title": "머큐리프로젝트, ‘MERCURY X’ 전략 실행형 AI 에이전트로 개편",
          "link": "https://finance.naver.com/item/news_read.naver?article_id=0003522426&office_id=025&code=100590&page=&sm=",
          "source": "중앙일보",
          "date": "2026.05.11"
        },
        {
          "title": "권순태 머큐리 대표 “데이터센터 타고 광통신 특수, 방산·드론이 미.....",
          "link": "https://finance.naver.com/item/news_read.naver?article_id=0005285184&office_id=015&code=100590&page=&sm=",
          "source": "한국경제",
          "date": "2026.05.11"
        },
        {
          "title": "[회생기로 STX] 위기의 전조 '3가지'",
          "link": "https://finance.naver.com/item/news_read.naver?article_id=0000083392&office_id=293&code=100590&page=&sm=",
          "source": "블로터",
          "date": "2026.04.24"
        },
        {
          "title": "\"AI 데이터센터로 광통신 특수…국방·드론 등 방산 영토 확장\"",
          "link": "https://finance.naver.com/item/news_read.naver?article_id=0005285063&office_id=015&code=100590&page=&sm=",
          "source": "한국경제",
          "date": "2026.05.10"
        },
        {
          "title": "상한가 찍더니 수익률 '-25%' 날벼락…양자컴 테마주 경고등",
          "link": "https://finance.naver.com/item/news_read.naver?article_id=0006263618&office_id=018&code=100590&page=&sm=",
          "source": "이데일리",
          "date": "2026.04.22"
        },
        {
          "title": "“이번엔 광통신” 엔비디아發 훈풍…광통신주 10% 급등 [줍줍 리포트....",
          "link": "https://finance.naver.com/item/news_read.naver?article_id=0004610047&office_id=011&code=100590&page=&sm=",
          "source": "서울경제",
          "date": "2026.04.13"
        }
      ],
      "sector": "통신장비",
      "is_52w_high": false,
      "source": "stockrise"
    },
    {
      "date": "20260507",
      "change_rate": 11.49,
      "close_price": 9900.0,
      "rise_reason": "계약 체결",
      "reason_confidence": "high",
      "reason_source": "stockrise",
      "reason_status": "filled",
      "theme_tag": "광통신(광케이블/광섬유 등)",
      "news": [
        {
          "title": "머큐리, LG유플러스에 와이파이6 공유기 150억원 공급",
          "link": "https://finance.naver.com/item/news_read.naver?article_id=0000082479&office_id=293&code=100590&page=&sm=",
          "source": "블로터",
          "date": "2026.04.09"
        },
        {
          "title": "머큐리, LG유플러스와 150억 규모 계약 체결",
          "link": "https://finance.naver.com/item/news_read.naver?article_id=0006253739&office_id=018&code=100590&page=&sm=",
          "source": "이데일리",
          "date": "2026.04.09"
        },
        {
          "title": "머큐리, LG유플러스와 150억 규모 공급계약 체결",
          "link": "https://finance.naver.com/item/news_read.naver?article_id=0002627344&office_id=016&code=100590&page=&sm=",
          "source": "헤럴드경제",
          "date": "2026.04.09"
        },
        {
          "title": "[회생기로 STX] 위기의 전조 '3가지'",
          "link": "https://finance.naver.com/item/news_read.naver?article_id=0000083392&office_id=293&code=100590&page=&sm=",
          "source": "블로터",
          "date": "2026.04.24"
        },
        {
          "title": "상한가 찍더니 수익률 '-25%' 날벼락…양자컴 테마주 경고등",
          "link": "https://finance.naver.com/item/news_read.naver?article_id=0006263618&office_id=018&code=100590&page=&sm=",
          "source": "이데일리",
          "date": "2026.04.22"
        },
        {
          "title": "“이번엔 광통신” 엔비디아發 훈풍…광통신주 10% 급등 [줍줍 리포트....",
          "link": "https://finance.naver.com/item/news_read.naver?article_id=0004610047&office_id=011&code=100590&page=&sm=",
          "source": "서울경제",
          "date": "2026.04.13"
        },
        {
          "title": "기업 공시 [4월 9일]",
          "link": "https://finance.naver.com/item/news_read.naver?article_id=0004609021&office_id=011&code=100590&page=&sm=",
          "source": "서울경제",
          "date": "2026.04.09"
        }
      ],
      "sector": "통신장비",
      "is_52w_high": false,
      "source": "stockrise"
    },
    {
      "date": "20260506",
      "change_rate": 19.84,
      "close_price": 8880.0,
      "rise_reason": "계약 체결",
      "reason_confidence": "high",
      "reason_source": "stockrise",
      "reason_status": "filled",
      "theme_tag": "광통신(광케이블/광섬유 등)",
      "news": [
        {
          "title": "머큐리, LG유플러스에 와이파이6 공유기 150억원 공급",
          "link": "https://finance.naver.com/item/news_read.naver?article_id=0000082479&office_id=293&code=100590&page=&sm=",
          "source": "블로터",
          "date": "2026.04.09"
        },
        {
          "title": "머큐리, LG유플러스와 150억 규모 계약 체결",
          "link": "https://finance.naver.com/item/news_read.naver?article_id=0006253739&office_id=018&code=100590&page=&sm=",
          "source": "이데일리",
          "date": "2026.04.09"
        },
        {
          "title": "머큐리, LG유플러스와 150억 규모 공급계약 체결",
          "link": "https://finance.naver.com/item/news_read.naver?article_id=0002627344&office_id=016&code=100590&page=&sm=",
          "source": "헤럴드경제",
          "date": "2026.04.09"
        },
        {
          "title": "[회생기로 STX] 위기의 전조 '3가지'",
          "link": "https://finance.naver.com/item/news_read.naver?article_id=0000083392&office_id=293&code=100590&page=&sm=",
          "source": "블로터",
          "date": "2026.04.24"
        },
        {
          "title": "상한가 찍더니 수익률 '-25%' 날벼락…양자컴 테마주 경고등",
          "link": "https://finance.naver.com/item/news_read.naver?article_id=0006263618&office_id=018&code=100590&page=&sm=",
          "source": "이데일리",
          "date": "2026.04.22"
        },
        {
          "title": "“이번엔 광통신” 엔비디아發 훈풍…광통신주 10% 급등 [줍줍 리포트....",
          "link": "https://finance.naver.com/item/news_read.naver?article_id=0004610047&office_id=011&code=100590&page=&sm=",
          "source": "서울경제",
          "date": "2026.04.13"
        },
        {
          "title": "기업 공시 [4월 9일]",
          "link": "https://finance.naver.com/item/news_read.naver?article_id=0004609021&office_id=011&code=100590&page=&sm=",
          "source": "서울경제",
          "date": "2026.04.09"
        }
      ],
      "sector": "통신장비",
      "is_52w_high": false,
      "source": "stockrise"
    },
    {
      "date": "20260504",
      "change_rate": 19.52,
      "close_price": 7410.0,
      "rise_reason": "계약 체결",
      "reason_confidence": "high",
      "reason_source": "stockrise",
      "reason_status": "filled",
      "theme_tag": "광통신(광케이블/광섬유 등)",
      "news": [
        {
          "title": "머큐리, LG유플러스에 와이파이6 공유기 150억원 공급",
          "link": "https://finance.naver.com/item/news_read.naver?article_id=0000082479&office_id=293&code=100590&page=&sm=",
          "source": "블로터",
          "date": "2026.04.09"
        },
        {
          "title": "머큐리, LG유플러스와 150억 규모 계약 체결",
          "link": "https://finance.naver.com/item/news_read.naver?article_id=0006253739&office_id=018&code=100590&page=&sm=",
          "source": "이데일리",
          "date": "2026.04.09"
        },
        {
          "title": "머큐리, LG유플러스와 150억 규모 공급계약 체결",
          "link": "https://finance.naver.com/item/news_read.naver?article_id=0002627344&office_id=016&code=100590&page=&sm=",
          "source": "헤럴드경제",
          "date": "2026.04.09"
        },
        {
          "title": "[회생기로 STX] 위기의 전조 '3가지'",
          "link": "https://finance.naver.com/item/news_read.naver?article_id=0000083392&office_id=293&code=100590&page=&sm=",
          "source": "블로터",
          "date": "2026.04.24"
        },
        {
          "title": "상한가 찍더니 수익률 '-25%' 날벼락…양자컴 테마주 경고등",
          "link": "https://finance.naver.com/item/news_read.naver?article_id=0006263618&office_id=018&code=100590&page=&sm=",
          "source": "이데일리",
          "date": "2026.04.22"
        },
        {
          "title": "“이번엔 광통신” 엔비디아發 훈풍…광통신주 10% 급등 [줍줍 리포트....",
          "link": "https://finance.naver.com/item/news_read.naver?article_id=0004610047&office_id=011&code=100590&page=&sm=",
          "source": "서울경제",
          "date": "2026.04.13"
        },
        {
          "title": "기업 공시 [4월 9일]",
          "link": "https://finance.naver.com/item/news_read.naver?article_id=0004609021&office_id=011&code=100590&page=&sm=",
          "source": "서울경제",
          "date": "2026.04.09"
        }
      ],
      "sector": "통신장비",
      "is_52w_high": false,
      "source": "stockrise"
    },
    {
      "date": "20260413",
      "change_rate": 21.85,
      "close_price": 11320.0,
      "rise_reason": "AI/반도체 테마",
      "reason_confidence": "mid",
      "reason_source": "news",
      "reason_status": "filled",
      "theme_tag": "",
      "news": [
        {
          "title": "[서울데이터랩]금일 코스닥 거래량 1위 대한광통신 거래대금 935억 돌...",
          "link": "https://n.news.naver.com/mnews/article/081/0003634733",
          "source": "서울신문",
          "date": "2026-04-13"
        },
        {
          "title": "“이번엔 광통신” 엔비디아發 훈풍…광통신주 10% 급등 [줍줍 리포트...",
          "link": "https://n.news.naver.com/mnews/article/011/0004610047",
          "source": "서울경제",
          "date": "2026-04-13"
        }
      ],
      "sector": "",
      "is_52w_high": true,
      "source": "estimated"
    },
    {
      "date": "20260409",
      "change_rate": 19.08,
      "close_price": 8800.0,
      "rise_reason": "52주 신고가 도달",
      "reason_confidence": "mid",
      "reason_source": "pattern",
      "reason_status": "filled",
      "theme_tag": "",
      "news": [
        {
          "title": "[서울데이터랩]금일 코스닥 거래량 1위 대한광통신 거래대금 무려 1조...",
          "link": "https://n.news.naver.com/mnews/article/081/0003634195",
          "source": "서울신문",
          "date": "2026-04-10"
        },
        {
          "title": "[서울데이터랩]빛과전자 30.00% 상한가 금일 증시 상승률 1위로 마감",
          "link": "https://n.news.naver.com/mnews/article/081/0003633912",
          "source": "서울신문",
          "date": "2026-04-09"
        },
        {
          "title": "머큐리, LG유플러스에 와이파이6 공유기 150억원 공급",
          "link": "https://n.news.naver.com/mnews/article/293/0000082479",
          "source": "블로터",
          "date": "2026-04-09"
        },
        {
          "title": "기업 공시 [4월 9일]",
          "link": "https://n.news.naver.com/mnews/article/011/0004609021",
          "source": "서울경제",
          "date": "2026-04-09"
        },
        {
          "title": "[서울데이터랩]금일 코스닥 거래량 1위 위지트 거래대금 무려 433억 돌...",
          "link": "https://n.news.naver.com/mnews/article/081/0003633831",
          "source": "서울신문",
          "date": "2026-04-09"
        }
      ],
      "sector": "",
      "is_52w_high": true,
      "source": "estimated"
    },
    {
      "date": "20260408",
      "change_rate": 29.88,
      "close_price": 7390.0,
      "rise_reason": "52주 신고가 도달",
      "reason_confidence": "mid",
      "reason_source": "pattern",
      "reason_status": "filled",
      "theme_tag": "",
      "news": [
        {
          "title": "[서울데이터랩]빛과전자 30.00% 상한가 금일 증시 상승률 1위로 마감",
          "link": "https://n.news.naver.com/mnews/article/081/0003633912",
          "source": "서울신문",
          "date": "2026-04-09"
        },
        {
          "title": "머큐리, LG유플러스에 와이파이6 공유기 150억원 공급",
          "link": "https://n.news.naver.com/mnews/article/293/0000082479",
          "source": "블로터",
          "date": "2026-04-09"
        },
        {
          "title": "기업 공시 [4월 9일]",
          "link": "https://n.news.naver.com/mnews/article/011/0004609021",
          "source": "서울경제",
          "date": "2026-04-09"
        },
        {
          "title": "[서울데이터랩]금일 코스닥 거래량 1위 위지트 거래대금 무려 433억 돌...",
          "link": "https://n.news.naver.com/mnews/article/081/0003633831",
          "source": "서울신문",
          "date": "2026-04-09"
        },
        {
          "title": "[서울데이터랩]‘애머릿지’ 30% 상한가…실시간 상승률 1위",
          "link": "https://n.news.naver.com/mnews/article/081/0003633732",
          "source": "서울신문",
          "date": "2026-04-09"
        }
      ],
      "sector": "",
      "is_52w_high": true,
      "source": "estimated"
    },
    {
      "date": "20260403",
      "change_rate": 17.76,
      "close_price": 6100.0,
      "rise_reason": "AI/반도체 테마",
      "reason_confidence": "mid",
      "reason_source": "news",
      "reason_status": "filled",
      "theme_tag": "",
      "news": [
        {
          "title": "[서울데이터랩]한국첨단소재 30.00% 상한가 금일 증시 상승률 1위로 마...",
          "link": "https://n.news.naver.com/mnews/article/081/0003632312",
          "source": "서울신문",
          "date": "2026-04-03"
        },
        {
          "title": "AI 시대 핵심으로 꼽히는 ‘광통신’ [매경 자이앤트]",
          "link": "https://n.news.naver.com/mnews/article/009/0005660478",
          "source": "매일경제",
          "date": "2026-04-03"
        },
        {
          "title": "광통신株 강세…한국첨단소재 상한가·기술 활용 기대감에 급등[특징...",
          "link": "https://n.news.naver.com/mnews/article/018/0006249219",
          "source": "이데일리",
          "date": "2026-04-03"
        },
        {
          "title": "6G상용화 기대감에 통신장비주 장초반 급등",
          "link": "https://n.news.naver.com/mnews/article/003/0013864973",
          "source": "뉴시스",
          "date": "2026-04-03"
        }
      ],
      "sector": "",
      "is_52w_high": false,
      "source": "estimated"
    },
    {
      "date": "20260401",
      "change_rate": 17.03,
      "close_price": 5600.0,
      "rise_reason": "시장 관심 증가",
      "reason_confidence": "low",
      "reason_source": "estimated",
      "reason_status": "filled",
      "theme_tag": "",
      "news": [
        {
          "title": "6G 준비에 광 네트워크까지…통신장비株 동반 급등",
          "link": "https://n.news.naver.com/mnews/article/008/0005338091",
          "source": "머니투데이",
          "date": "2026-04-01"
        }
      ],
      "sector": "",
      "is_52w_high": false,
      "source": "estimated"
    },
    {
      "date": "20260324",
      "change_rate": 29.81,
      "close_price": 5900.0,
      "rise_reason": "AI/반도체 테마",
      "reason_confidence": "mid",
      "reason_source": "news",
      "reason_status": "filled",
      "theme_tag": "",
      "news": [
        {
          "title": "[서울데이터랩]금일 코스닥 거래량 1위 빛과전자 거래대금 무려 1058억...",
          "link": "https://n.news.naver.com/mnews/article/081/0003629217",
          "source": "서울신문",
          "date": "2026-03-25"
        },
        {
          "title": "한국첨단소재, 광통신주 기대 부각에 이틀째 '상한가'[특징주]",
          "link": "https://n.news.naver.com/mnews/article/018/0006242257",
          "source": "이데일리",
          "date": "2026-03-25"
        },
        {
          "title": "엔비디아發 광반도체 열풍…관련 테마 6종목 일제히 上[핫종목](종합...",
          "link": "https://n.news.naver.com/mnews/article/421/0008846597",
          "source": "뉴스1",
          "date": "2026-03-24"
        },
        {
          "title": "[서울데이터랩]와이어블 30.00% 상한가 금일 증시 상승률 1위로 마감",
          "link": "https://n.news.naver.com/mnews/article/081/0003628891",
          "source": "서울신문",
          "date": "2026-03-24"
        },
        {
          "title": "차세대 AI 데이터처리 기술로 주목받는 '이 테마'",
          "link": "https://n.news.naver.com/mnews/article/008/0005334214",
          "source": "머니투데이",
          "date": "2026-03-24"
        }
      ],
      "sector": "",
      "is_52w_high": true,
      "source": "estimated"
    },
    {
      "date": "20260313",
      "change_rate": 11.16,
      "close_price": 5180.0,
      "rise_reason": "태양광/재생에너지",
      "reason_confidence": "mid",
      "reason_source": "news",
      "reason_status": "filled",
      "theme_tag": "",
      "news": [
        {
          "title": "신재생·통신장비주 동반 강세…K증시 신고가 랠리 주도 [매경 자이앤...",
          "link": "https://n.news.naver.com/mnews/article/009/0005649365",
          "source": "매일경제",
          "date": "2026-03-12"
        },
        {
          "title": "2조 vs 2조…개인-외인 대치 속 코스피 0.5%↓",
          "link": "https://n.news.naver.com/mnews/article/215/0001244935",
          "source": "한국경제TV",
          "date": "2026-03-12"
        },
        {
          "title": "머큐리, 글로벌 광케이블 수요 확대로 올해 본격 매출 확장 추진",
          "link": "https://n.news.naver.com/mnews/article/008/0005328861",
          "source": "머니투데이",
          "date": "2026-03-12"
        }
      ],
      "sector": "",
      "is_52w_high": true,
      "source": "estimated"
    },
    {
      "date": "20260312",
      "change_rate": 12.56,
      "close_price": 4660.0,
      "rise_reason": "태양광/재생에너지",
      "reason_confidence": "mid",
      "reason_source": "news",
      "reason_status": "filled",
      "theme_tag": "",
      "news": [
        {
          "title": "신재생·통신장비주 동반 강세…K증시 신고가 랠리 주도 [매경 자이앤...",
          "link": "https://n.news.naver.com/mnews/article/009/0005649365",
          "source": "매일경제",
          "date": "2026-03-12"
        },
        {
          "title": "2조 vs 2조…개인-외인 대치 속 코스피 0.5%↓",
          "link": "https://n.news.naver.com/mnews/article/215/0001244935",
          "source": "한국경제TV",
          "date": "2026-03-12"
        },
        {
          "title": "머큐리, 글로벌 광케이블 수요 확대로 올해 본격 매출 확장 추진",
          "link": "https://n.news.naver.com/mnews/article/008/0005328861",
          "source": "머니투데이",
          "date": "2026-03-12"
        }
      ],
      "sector": "",
      "is_52w_high": true,
      "source": "estimated"
    },
    {
      "date": "20260311",
      "change_rate": 12.2,
      "close_price": 4140.0,
      "rise_reason": "태양광/재생에너지",
      "reason_confidence": "mid",
      "reason_source": "news",
      "reason_status": "filled",
      "theme_tag": "",
      "news": [
        {
          "title": "신재생·통신장비주 동반 강세…K증시 신고가 랠리 주도 [매경 자이앤...",
          "link": "https://n.news.naver.com/mnews/article/009/0005649365",
          "source": "매일경제",
          "date": "2026-03-12"
        },
        {
          "title": "2조 vs 2조…개인-외인 대치 속 코스피 0.5%↓",
          "link": "https://n.news.naver.com/mnews/article/215/0001244935",
          "source": "한국경제TV",
          "date": "2026-03-12"
        },
        {
          "title": "머큐리, 글로벌 광케이블 수요 확대로 올해 본격 매출 확장 추진",
          "link": "https://n.news.naver.com/mnews/article/008/0005328861",
          "source": "머니투데이",
          "date": "2026-03-12"
        }
      ],
      "sector": "",
      "is_52w_high": true,
      "source": "estimated"
    },
    {
      "date": "20260310",
      "change_rate": 14.6,
      "close_price": 3690.0,
      "rise_reason": "시장 관심 증가",
      "reason_confidence": "low",
      "reason_source": "estimated",
      "reason_status": "filled",
      "theme_tag": "",
      "news": [],
      "sector": "",
      "is_52w_high": false,
      "source": "estimated"
    }
  ],
  "stats": {
    "count_10": 14,
    "count_15": 9,
    "count_20": 3,
    "count_limit": 0,
    "count_recent": 0,
    "avg_rate": 18.07
  },
  "built_at": "2026-06-21T02:09:41"
}