{
  "ticker": "192410",
  "name": "오늘이엔엠",
  "market": "KOSDAQ",
  "events": [
    {
      "date": "20260508",
      "change_rate": 22.26,
      "close_price": 6590.0,
      "rise_reason": "수출 관련 뉴스",
      "reason_confidence": "high",
      "reason_source": "stockrise",
      "reason_status": "filled",
      "theme_tag": "로봇(산업용/협동로봇 등)",
      "news": [
        {
          "title": "[클릭 e종목]\"오늘이엔엠, AT&T·테슬라가 선택한 초연결 광통신 수...",
          "link": "https://finance.naver.com/item/news_read.naver?article_id=0005752266&office_id=277&code=192410&page=&sm=",
          "source": "아시아경제",
          "date": "2026.04.21"
        },
        {
          "title": "오늘이엔엠, 파리·로마 지하철 5G 터널용 안테나 공급 완료",
          "link": "https://finance.naver.com/item/news_read.naver?article_id=0013874430&office_id=003&code=192410&page=&sm=",
          "source": "뉴시스",
          "date": "2026.04.08"
        },
        {
          "title": "오늘이엔엠, '파리·로마 지하철' 5G 안테나 공급",
          "link": "https://finance.naver.com/item/news_read.naver?article_id=0005504270&office_id=014&code=192410&page=&sm=",
          "source": "파이낸셜뉴스",
          "date": "2026.04.08"
        },
        {
          "title": "오늘이엔엠, 파리·로마 지하철 5G 터널용 안테나 공급 완료…유럽 철...",
          "link": "https://finance.naver.com/item/news_read.naver?article_id=0005746433&office_id=277&code=192410&page=&sm=",
          "source": "아시아경제",
          "date": "2026.04.08"
        },
        {
          "title": "오늘이엔엠, 글로벌 메이저 DAS 장비 연동…파리·로마 지하철 5G ...",
          "link": "https://finance.naver.com/item/news_read.naver?article_id=0006252633&office_id=018&code=192410&page=&sm=",
          "source": "이데일리",
          "date": "2026.04.08"
        },
        {
          "title": "오늘이엔엠, 美 AT&T·에릭슨 140억 달러 규모 프로젝트 핵심 파트...",
          "link": "https://finance.naver.com/item/news_read.naver?article_id=0006247432&office_id=018&code=192410&page=&sm=",
          "source": "이데일리",
          "date": "2026.04.01"
        },
        {
          "title": "오늘이엔엠 \"5G 통신장비 수출 중심 체질 개선…올해 퀀텀점프\"",
          "link": "https://finance.naver.com/item/news_read.naver?article_id=0013859247&office_id=003&code=192410&page=&sm=",
          "source": "뉴시스",
          "date": "2026.04.01"
        },
        {
          "title": "오늘이엔엠, 북미 중심 수출 체질 전환 성공…5G 장비 매출 '퀀텀점...",
          "link": "https://finance.naver.com/item/news_read.naver?article_id=0005743235&office_id=277&code=192410&page=&sm=",
          "source": "아시아경제",
          "date": "2026.04.01"
        },
        {
          "title": "오늘이엔엠, 5G 통신장비 수출 중심 체질 개선…북미 매출 전년비 1...",
          "link": "https://finance.naver.com/item/news_read.naver?article_id=0006247142&office_id=018&code=192410&page=&sm=",
          "source": "이데일리",
          "date": "2026.04.01"
        },
        {
          "title": "오늘이엔엠, 美 AT&T·에릭슨 '140억 달러 규모 오픈랜' 프로젝트...",
          "link": "https://finance.naver.com/item/news_read.naver?article_id=0005741231&office_id=277&code=192410&page=&sm=",
          "source": "아시아경제",
          "date": "2026.03.27"
        }
      ],
      "sector": "통신장비",
      "is_52w_high": false,
      "source": "stockrise"
    }
  ],
  "stats": {
    "count_10": 1,
    "count_15": 1,
    "count_20": 1,
    "count_limit": 0,
    "count_recent": 0,
    "avg_rate": 22.26
  },
  "built_at": "2026-06-19T20:43:55"
}