{
  "ticker": "434480",
  "name": "모니터랩",
  "market": "KOSDAQ",
  "events": [
    {
      "date": "20260415",
      "change_rate": 10.71,
      "close_price": 4395.0,
      "trading_volume": 5004785,
      "trading_value": 21996030075,
      "rise_reason": "양자 자사주 소각",
      "reason_confidence": "high",
      "reason_source": "stockrise",
      "reason_status": "filled",
      "theme_tag": "보안주(정보)",
      "news": [
        {
          "title": "UCLM 연동 범위 확대… 모니터랩·시트릭스·AWS까지 지원",
          "link": "https://finance.naver.com/item/news_read.naver?article_id=0003021274&office_id=029&code=434480&page=&sm=",
          "source": "디지털타임스",
          "date": "2026.04.13"
        },
        {
          "title": "모니터랩, '중소기업 클라우드 사업' 공급기업 선정",
          "link": "https://finance.naver.com/item/news_read.naver?article_id=0003415067&office_id=030&code=434480&page=&sm=",
          "source": "전자신문",
          "date": "2026.04.06"
        },
        {
          "title": "모니터랩, 34.5억 규모 상환전환우선주 소각 결정",
          "link": "https://finance.naver.com/item/news_read.naver?article_id=0006247376&office_id=018&code=434480&page=&sm=",
          "source": "이데일리",
          "date": "2026.04.01"
        },
        {
          "title": "모니터랩, 35억 규모 상환전환우선주 소각 결정",
          "link": "https://finance.naver.com/item/news_read.naver?article_id=0000081994&office_id=293&code=434480&page=&sm=",
          "source": "블로터",
          "date": "2026.04.01"
        },
        {
          "title": "모니터랩, AI 바우처 사업 3년 연속 참여…보안 솔루션 공급",
          "link": "https://finance.naver.com/item/news_read.naver?article_id=0003411721&office_id=030&code=434480&page=&sm=",
          "source": "전자신문",
          "date": "2026.03.26"
        },
        {
          "title": "모니터랩, AI 바우처 지원사업 공급사 선정…3년 연속",
          "link": "https://finance.naver.com/item/news_read.naver?article_id=0002222112&office_id=138&code=434480&page=&sm=",
          "source": "디지털데일리",
          "date": "2026.03.26"
        },
        {
          "title": "모니터랩, ‘2026년 AI 바우처 지원사업’ 공급기업 선정",
          "link": "https://finance.naver.com/item/news_read.naver?article_id=0002416151&office_id=092&code=434480&page=&sm=",
          "source": "지디넷코리아",
          "date": "2026.03.26"
        },
        {
          "title": "모니터랩, 'eGISEC 2026'서 N2SF 대응 솔루션 선봬",
          "link": "https://finance.naver.com/item/news_read.naver?article_id=0002415914&office_id=092&code=434480&page=&sm=",
          "source": "지디넷코리아",
          "date": "2026.03.24"
        },
        {
          "title": "[DD퇴근길] \"맥북 프로 싹 바뀐다\"…애플 리디자인 통할까",
          "link": "https://finance.naver.com/item/news_read.naver?article_id=0002221834&office_id=138&code=434480&page=&sm=",
          "source": "디지털데일리",
          "date": "2026.03.24"
        },
        {
          "title": "초거대 AI가 사이버재앙 될라…양자·보안주 급등",
          "link": "https://finance.naver.com/item/news_read.naver?article_id=0005665695&office_id=009&code=434480&page=&sm=",
          "source": "매일경제",
          "date": "2026.04.14"
        }
      ],
      "sector": "소프트웨어",
      "is_52w_high": false,
      "source": "stockrise"
    },
    {
      "date": "20260414",
      "change_rate": 17.11,
      "close_price": 3970.0,
      "trading_volume": 4730984,
      "trading_value": 18782006480,
      "rise_reason": "양자 자사주 소각",
      "reason_confidence": "high",
      "reason_source": "stockrise",
      "reason_status": "filled",
      "theme_tag": "보안주(정보)",
      "news": [
        {
          "title": "초거대 AI가 사이버재앙 될라…양자·보안주 급등",
          "link": "https://finance.naver.com/item/news_read.naver?article_id=0005665695&office_id=009&code=434480&page=&sm=",
          "source": "매일경제"
        },
        {
          "title": "[서울데이터랩]‘에프알텍’ 29.97% 상한가…실시간 상승률 1위",
          "link": "https://finance.naver.com/item/news_read.naver?article_id=0003635043&office_id=081&code=434480&page=&sm=",
          "source": "서울신문"
        },
        {
          "title": "UCLM 연동 범위 확대… 모니터랩·시트릭스·AWS까지 지원",
          "link": "https://finance.naver.com/item/news_read.naver?article_id=0003021274&office_id=029&code=434480&page=&sm=",
          "source": "디지털타임스"
        },
        {
          "title": "모니터랩, '중소기업 클라우드 사업' 공급기업 선정",
          "link": "https://finance.naver.com/item/news_read.naver?article_id=0003415067&office_id=030&code=434480&page=&sm=",
          "source": "전자신문"
        },
        {
          "title": "기업 공시 [4월 1일]",
          "link": "https://finance.naver.com/item/news_read.naver?article_id=0004606030&office_id=011&code=434480&page=&sm=",
          "source": "서울경제"
        },
        {
          "title": "모니터랩, 34.5억 규모 상환전환우선주 소각 결정",
          "link": "https://finance.naver.com/item/news_read.naver?article_id=0006247376&office_id=018&code=434480&page=&sm=",
          "source": "이데일리"
        },
        {
          "title": "모니터랩, 35억 규모 상환전환우선주 소각 결정",
          "link": "https://finance.naver.com/item/news_read.naver?article_id=0000081994&office_id=293&code=434480&page=&sm=",
          "source": "블로터"
        },
        {
          "title": "모니터랩, AI 바우처 사업 3년 연속 참여…보안 솔루션 공급",
          "link": "https://finance.naver.com/item/news_read.naver?article_id=0003411721&office_id=030&code=434480&page=&sm=",
          "source": "전자신문"
        },
        {
          "title": "모니터랩, AI 바우처 지원사업 공급사 선정…3년 연속",
          "link": "https://finance.naver.com/item/news_read.naver?article_id=0002222112&office_id=138&code=434480&page=&sm=",
          "source": "디지털데일리"
        },
        {
          "title": "모니터랩, ‘2026년 AI 바우처 지원사업’ 공급기업 선정",
          "link": "https://finance.naver.com/item/news_read.naver?article_id=0002416151&office_id=092&code=434480&page=&sm=",
          "source": "지디넷코리아"
        }
      ],
      "sector": "소프트웨어",
      "is_52w_high": false,
      "source": "stockrise"
    },
    {
      "date": "20260305",
      "change_rate": 11.16,
      "close_price": 3485.0,
      "rise_reason": "보안주(정보) 테마 강세",
      "reason_confidence": "low",
      "reason_source": "theme",
      "reason_status": "filled",
      "theme_tag": "보안주(정보)",
      "news": [
        {
          "title": "작년 글로벌 보안 M&amp;A '역대 최대'…한국은 2건뿐",
          "link": "https://n.news.naver.com/mnews/article/030/0003404786",
          "source": "전자신문",
          "date": "2026-03-05"
        },
        {
          "title": "모니터랩, 정기주총서 직원 1명에 스톡옵션 부여",
          "link": "https://n.news.naver.com/mnews/article/293/0000080336",
          "source": "블로터",
          "date": "2026-03-05"
        }
      ],
      "sector": "소프트웨어",
      "is_52w_high": false,
      "source": "estimated",
      "trading_volume": 90944,
      "trading_value": 316939840,
      "market_cap": 42851612903
    }
  ],
  "stats": {
    "count_10": 3,
    "count_15": 1,
    "count_20": 0,
    "count_limit": 0,
    "count_recent": 0,
    "avg_rate": 12.99
  },
  "built_at": "2026-07-24T18:17:14"
}